README.md
__init__.py
conftest.py
libtbx_refresh.py
run_tests.py
setup.py
algorithms/__init__.py
algorithms/background/__init__.py
algorithms/background/modeller.py
algorithms/background/glm/__init__.py
algorithms/background/glm/algorithm.py
algorithms/background/gmodel/__init__.py
algorithms/background/gmodel/algorithm.py
algorithms/background/gmodel/modeller.py
algorithms/background/median/__init__.py
algorithms/background/median/algorithm.py
algorithms/background/simple/__init__.py
algorithms/background/simple/algorithm.py
algorithms/background_lookup/__init__.py
algorithms/background_lookup/background_and_gain.py
algorithms/background_lookup/detector_noise.py
algorithms/centroid/__init__.py
algorithms/centroid/centroid_px_to_mm.py
algorithms/centroid/simple/__init__.py
algorithms/centroid/simple/algorithm.py
algorithms/clustering/__init__.py
algorithms/clustering/observers.py
algorithms/clustering/plots.py
algorithms/clustering/test_observers.py
algorithms/clustering/test_plots.py
algorithms/clustering/test_unit_cell.py
algorithms/clustering/unit_cell.py
algorithms/filtering/__init__.py
algorithms/image/__init__.py
algorithms/image/centroid/__init__.py
algorithms/image/connected_components/__init__.py
algorithms/image/fill_holes/__init__.py
algorithms/image/filter/__init__.py
algorithms/image/threshold/__init__.py
algorithms/indexing/__init__.py
algorithms/indexing/compare_orientation_matrices.py
algorithms/indexing/fft1d.py
algorithms/indexing/fft3d.py
algorithms/indexing/indexer.py
algorithms/indexing/known_orientation.py
algorithms/indexing/max_cell.py
algorithms/indexing/nave_parameters.py
algorithms/indexing/nearest_neighbor.py
algorithms/indexing/real_space_grid_search.py
algorithms/indexing/refinement.py
algorithms/indexing/stills_indexer.py
algorithms/indexing/symmetry.py
algorithms/indexing/test_max_cell.py
algorithms/integration/__init__.py
algorithms/integration/filtering.py
algorithms/integration/image_integrator.py
dials.egg-info/PKG-INFO
dials.egg-info/SOURCES.txt
dials.egg-info/dependency_links.txt
dials.egg-info/not-zip-safe
dials.egg-info/requires.txt
dials.egg-info/top_level.txt
